AUTHORS.md
CHANGELOG.rst
LICENSE.txt
MANIFEST.in
README.rst
setup.cfg
setup.py
Eve_Statsd.egg-info/PKG-INFO
Eve_Statsd.egg-info/SOURCES.txt
Eve_Statsd.egg-info/dependency_links.txt
Eve_Statsd.egg-info/requires.txt
Eve_Statsd.egg-info/top_level.txt
eve_statsd/__init__.py
eve_statsd/hooks.py
eve_statsd/test/__init__.py
eve_statsd/test/test_statd.py