Metadata-Version: 1.1
Name: Eve-Statsd
Version: 0.0.2
Summary: Statsd integration for eve
Home-page: https://github.com/tarzan0820/eve-statsd
Author: Salton Massally
Author-email: salton.massally@gmail.com
License: GNU GENERAL PUBLIC LICENSE
